AUTHORS.rst
CHANGELOG.rst
LICENSE
MANIFEST.in
README.rst
setup.py
ua_mapper/__init__.py
ua_mapper/updatewurfl.py
ua_mapper/wsgi.py
ua_mapper/wurfl.py
ua_mapper/wurfl2python.py
wsgi_ua_mapper.egg-info/PKG-INFO
wsgi_ua_mapper.egg-info/SOURCES.txt
wsgi_ua_mapper.egg-info/dependency_links.txt
wsgi_ua_mapper.egg-info/not-zip-safe
wsgi_ua_mapper.egg-info/requires.txt
wsgi_ua_mapper.egg-info/top_level.txt