Metadata-Version: 1.0
Name: wsgi-ua-mapper
Version: 0.0.4
Summary: WSGI app mapping requesting User Agent to arbitrary value through user defined module. Utilizes Wurfl to deliver requesting device info.
Home-page: http://github.com/praekelt/wsgi-ua-mapper
Author: Praekelt Foundation
Author-email: dev@praekelt.com
License: BSD
Platform: UNKNOWN
Classifier: Programming Language :: Python
Classifier: License :: OSI Approved :: BSD License
Classifier: Development Status :: 4 - Beta
Classifier: Operating System :: OS Independent
Classifier: Intended Audience :: Developers
Classifier: Topic :: Internet :: WWW/HTTP :: Dynamic Content
